mensajes/__init__.py
mensajes/adios/__init__.py
mensajes/adios/despedida.py
mensajes/hola/__init__.py
mensajes/hola/saludos.py
tests/__init__.py
tests/test_hola.py
mensajes_kelvinnieves-5.0.dist-info/LICENSE
mensajes_kelvinnieves-5.0.dist-info/METADATA
mensajes_kelvinnieves-5.0.dist-info/WHEEL
mensajes_kelvinnieves-5.0.dist-info/top_level.txt
mensajes_kelvinnieves-5.0.dist-info/RECORD
