Metadata-Version: 2.1
Name: mensajes-kelvinnieves
Version: 5.0
Summary: un Paquete para saludar y despedir
Home-page: https://kenmaster.cl
Author: Kenmaster
Author-email: kenmaster@gmail.com
Classifier: Environment :: Console
Classifier: Intended Audience :: Developers
Classifier: License :: OSI Approved :: MIT License
Classifier: Operating System :: OS Independent
Classifier: Programming Language :: Python
Classifier: Programming Language :: Python :: 3.10
Classifier: Topic :: Utilities
License-File: LICENSE
Requires-Dist: numpy (==1.23.3)
